EmojiText/EmojiText.py
EmojiText/__init__.py
emojis/293ab0f0-d19d-480f-8b01-c9f2197d44cc-8.png
EmojiText-0.2.dist-info/METADATA
EmojiText-0.2.dist-info/WHEEL
EmojiText-0.2.dist-info/top_level.txt
EmojiText-0.2.dist-info/RECORD
