Metadata-Version: 2.1
Name: EmojiText
Version: 0.2
Summary: A library to parse and display custom emojis in text
Home-page: https://github.com/LacyCat/EmojiText
Author: LacyCat1807
Classifier: Programming Language :: Python :: 3
Classifier: Operating System :: OS Independent
Requires-Python: >=3.6
Requires-Dist: Pillow
